tffm2/__init__.py
tffm2/base.py
tffm2/core.py
tffm2/models.py
tffm2/utils.py
tffm2-0.0.23.dist-info/METADATA
tffm2-0.0.23.dist-info/WHEEL
tffm2-0.0.23.dist-info/top_level.txt
tffm2-0.0.23.dist-info/RECORD
