Metadata-Version: 2.1
Name: tffm2
Version: 0.0.23
Summary: TensforFlow implementation of arbitrary order Factorization Machine
Home-page: https://github.com/jamborta/tffm2
Author: UNKNOWN
Author-email: UNKNOWN
License: MIT
Platform: UNKNOWN
Classifier: Intended Audience :: Science/Research
Classifier: Topic :: Scientific/Engineering
Classifier: Programming Language :: Python :: 3
Requires-Dist: scikit-learn
Requires-Dist: numpy
Requires-Dist: tqdm
